Workbook

Sheet Start Here
B2: Maximo Starter Glossary: Full Term Map
B3: Content plan for an open, plain-English Maximo glossary and learning site. Built around one fictional organization so every example connects.
B5: What this is | C5: The complete list of terms for the site, grouped into 14 modules, with a first-draft definition, where it lives in Maximo, a worked example from Riverbend Water, related terms, common misconceptions and version notes.
B6: Total terms | C6: =COUNTA('Term Map'!D2:D319) -> 318
B7: Verified so far | C7: =COUNTIF('Term Map'!N2:N319,"Verified")+COUNTIF('Term Map'!N2:N319,"Published") -> 0
B8: Percent verified | C8: =IFERROR(C7/C6,0) -> 0
B9: How to use it | C9: 1. Read the Riverbend Water tab first so the examples make sense. 2. Work through the Term Map, rewriting each definition in your own voice. The drafts are a starting point, not the final copy. 3. Have a hands-on Maximo practitioner check each row against IBM Docs for your target version, then set Review Status to Verified. 4. Use the Learning Paths tab to build guided tracks on the site. 5. The Page Slug column gives a ready-made URL for each term page.
B10: Review Status values | C10: Not started > Drafted > In review > Verified > Published. Every row starts as Drafted.
B11: Columns you edit | C11: Review Status, Reviewer, Reviewer Notes, and any wording you want to change. Everything else is reference content.
B12: Example row | C12: M03-005 'Work Order Lifecycle / Status Flow' shows the expected depth: definition, status codes, a Riverbend example, related terms and a misconception.
B13: Accuracy note | C13: Version facts were checked against IBM sources in October 2026 (see Sources tab). Field names, statuses, licensing values and app availability can change between releases and are configurable per customer, so confirm against IBM Docs for the version you write about.
B14: Disclaimer for the site | C14: Independent community resource. Not affiliated with or endorsed by IBM. IBM, Maximo and related names are trademarks of IBM Corp. Riverbend Water Authority is fictional.

Sheet Term Map
A1: ID | B1: Module | C1: Sub-area | D1: Term | E1: Field / Code | F1: Plain-English Definition | G1: Where in Maximo | H1: Riverbend Water Example | I1: Related Terms | J1: Common Misconception | K1: Difficulty | L1: Version Note (7.6 / MAS) | M1: Verify In (IBM Docs area) | N1: Review Status | O1: Reviewer | P1: Reviewer Notes | Q1: Page Slug
A2: M01-001 | B2: 01 Foundations and Structure | C2: Multisite structure | D2: Organization | E2: ORGID | F2: The top level of how a company is set up in Maximo. An organization holds the financial rules: base currency, general ledger structure, and many default options that every site under it follows. | G2: Organizations app (Administration) | H2: Riverbend Water Authority is one organization, RWA, with Canadian dollars as its base currency. | I2: Site; Item Set; Company Set; Base Currency; GL Account | J2: People often think an organization is just a label. It actually controls financial behavior, so splitting one company into several organizations has real consequences. | K2: Beginner | L2: Same concept in 7.6 and MAS. | M2: IBM Docs > Maximo Manage > Administering > Organizations and sites | N2: Drafted | Q2: organization
A3: M01-002 | B3: 01 Foundations and Structure | C3: Multisite structure | D3: Site | E3: SITEID | F3: An operational place that belongs to an organization, like a plant, campus or yard. Most day to day records, including work orders, assets and storeroom inventory, are stored at the site level. | G3: Organizations app, Sites action | H3: RWA has three sites: TP1 (Riverbend Treatment Plant), DIST (Distribution Network) and FLEET (Fleet Yard). | I3: Organization; Default Insert Site; Multisite | J3: A site is not the same as a location. A site is a top-level bucket, and locations are the places inside it. | K3: Beginner | M3: IBM Docs > Maximo Manage > Administering > Organizations and sites | N3: Drafted | Q3: site
A4: M01-003 | B4: 01 Foundations and Structure | C4: Multisite structure | D4: Item Set | E4: ITEMSETID | F4: A shared catalog of items and tools that one or more organizations can use. It lets several organizations share the same item numbers and descriptions. | G4: Sets app | H4: RWA uses the item set RWAITEMS, so seal kit 1001-SEAL means the same thing at every site. | I4: Item Master; Company Set; Organization | J4: Item sets hold the item definition only. Stock levels and costs live at the storeroom level, not in the item set. | K4: Intermediate | M4: IBM Docs > Maximo Manage > Administering > Organizations and sites | N4: Drafted | Q4: item-set
A5: M01-004 | B5: 01 Foundations and Structure | C5: Multisite structure | D5: Company Set | E5: COMPANYSETID | F5: A shared list of vendors, manufacturers and other companies that organizations can use. Like item sets, it avoids keeping duplicate vendor records. | G5: Sets app; Company Master app | H5: Northshore Pump Supply is set up once in the RWA company set and used for purchasing at all three sites. | I5: Company / Vendor | K5: Intermediate | M5: IBM Docs > Maximo Manage > Administering > Organizations and sites | N5: Drafted | Q5: company-set
A6: M01-005 | B6: 01 Foundations and Structure | C6: Multisite structure | D6: Multisite | F6: Maximo's ability to run many sites and organizations in one system while keeping data separated where it needs to be. Security, numbering and defaults can all be controlled by site. | G6: Organizations app; Security Groups app | H6: A planner at TP1 only sees TP1 work orders, while the asset manager at head office sees all three sites. | I6: Organization; Site; Security Group; Site-level vs Org-level vs System-level Object | K6: Intermediate | M6: IBM Docs > Maximo Manage > Administering > Organizations and sites | N6: Drafted | Q6: multisite
A7: M01-006 | B7: 01 Foundations and Structure | C7: Multisite structure | D7: Default Insert Site | F7: The site that new records are automatically created in for a user. It is set on each user's profile and saves users from picking a site every time. | G7: Users app; user profile (Default Information) | H7: Ana, a TP1 planner, has TP1 as her default insert site, so every new work order she creates lands at the plant. | I7: Site; User; Person | J7: If a user creates records at the wrong site, the default insert site is the first thing to check. | K7: Beginner | M7: IBM Docs > Maximo Manage > Administering > Organizations and sites | N7: Drafted | Q7: default-insert-site
A8: M01-007 | B8: 01 Foundations and Structure | C8: Multisite structure | D8: Site-level vs Org-level vs System-level Object | F8: Every record type in Maximo belongs at a certain level. Work orders are site-level, chart of account settings are org-level, and things like users and domains are system-level. | G8: Database Configuration app (Level field on each object) | H8: Two sites can each have a work order number 1001 because work orders are site-level, but there is only one user named ANAPLANNER. | I8: Organization; Site; Database Configuration | K8: Advanced | M8: IBM Docs > Maximo Manage > Administering > Organizations and sites | N8: Drafted | Q8: site-level-vs-org-level-vs-system-level-object
A9: M01-008 | B9: 01 Foundations and Structure | C9: Multisite structure | D9: Base Currency | F9: The main currency an organization uses for its financial records. Transactions in other currencies are converted to it using exchange rates. | G9: Organizations app; Currency Code app | H9: RWA's base currency is CAD. A pump bought in USD is converted to CAD on the PO. | I9: Currency Code / Exchange Rate; Organization | K9: Intermediate | M9: IBM Docs > Maximo Manage > Administering > Organizations and sites | N9: Drafted | Q9: base-currency
A10: M01-009 | B10: 01 Foundations and Structure | C10: Record basics | D10: Application | F10: A screen or set of screens in Maximo built around one main type of record, such as Work Order Tracking or Assets. Users open applications from the navigator menu. | G10: Navigator / side menu | H10: A technician opens the Work Order Tracking application to see open jobs. | I10: Module; Object (Maximo Business Object / MBO); Start Center; Role-based Application | K10: Beginner | L10: In MAS 9.1 and later, a new unified navigation bar organizes applications across the suite. | M10: IBM Docs > Maximo Manage > Administering > Organizations and sites | N10: Drafted | Q10: application
A11: M01-010 | B11: 01 Foundations and Structure | C11: Record basics | D11: Module | F11: A group of related applications in the menu, such as Work Orders, Inventory or Purchasing. | G11: Navigator / side menu | H11: The Inventory module includes Item Master, Inventory, Storerooms and Issues and Transfers. | I11: Application | K11: Beginner | M11: IBM Docs > Maximo Manage > Administering > Organizations and sites | N11: Drafted | Q11: module
A12: M01-011 | B12: 01 Foundations and Structure | C12: Record basics | D12: Record | F12: A single entry in an application, like one asset, one work order or one purchase order. | G12: All applications | H12: Work order 50231 for the P-101 seal leak is one record. | I12: Application; Object (Maximo Business Object / MBO); Status | K12: Beginner | M12: IBM Docs > Maximo Manage > Administering > Organizations and sites | N12: Drafted | Q12: record
A13: M01-012 | B13: 01 Foundations and Structure | C13: Record basics | D13: Status | E13: STATUS | F13: The stage a record is in, which controls what can be done with it next. Most major records have their own list of statuses and many keep a full status history. | G13: Change Status action in most applications | H13: Work order 50231 moves from WAPPR to APPR to INPRG to COMP to CLOSE. | I13: Synonym Domain; Work Order Lifecycle / Status Flow; Work Order Status History | J13: Status values can be renamed for users (synonyms), but Maximo's logic runs on the internal value underneath. | K13: Beginner | M13: IBM Docs > Maximo Manage > Administering > Organizations and sites | N13: Drafted | Q13: status
A14: M01-013 | B14: 01 Foundations and Structure | C14: Record basics | D14: Long Description | F14: A larger free-text field attached to many description fields, used for detailed notes that do not fit in the short description. | G14: Long description icon next to a Description field | H14: The work order's short description says 'P-101 seal leaking' and the long description explains when and where it was spotted. | I14: Work Log; Attachments | K14: Beginner | M14: IBM Docs > Maximo Manage > Administering > Organizations and sites | N14: Drafted | Q14: long-description
A15: M01-014 | B15: 01 Foundations and Structure | C15: Record basics | D15: Attachments | E15: DOCLINKS | F15: Files or URLs linked to a record, like manuals, photos, drawings or permits. Attachments can be organized into folders and copied between records. | G15: Attachments section on most applications | H15: The P-101 pump manual PDF is attached to the asset and automatically shows on its work orders. | I15: Long Description; Work Log | K15: Beginner | L15: Older docs refer to this feature as Doclinks. | M15: IBM Docs > Maximo Manage > Administering > Organizations and sites | N15: Drafted | Q15: attachments
A16: M01-015 | B16: 01 Foundations and Structure | C16: Record basics | D16: Work Log | E16: WORKLOG | F16: A running set of notes on a record such as a work order or service request, used to record updates, findings and communication over time. | G16: Log tab or Work Log section | H16: The mechanic adds a log entry: 'Seal faces scored, replaced with kit 1001-SEAL.' | I16: Long Description | K16: Beginner | M16: IBM Docs > Maximo Manage > Administering > Organizations and sites | N16: Drafted | Q16: work-log
A17: M01-016 | B17: 01 Foundations and Structure | C17: Record basics | D17: Query / Saved Query | F17: A search you save so you can reuse it. Queries filter the list of records in an application and can be shared with other users or used on Start Centers. | G17: List tab in each application; Save Query action | H17: Ana saves a query called 'My TP1 backlog' that shows approved work orders at TP1 assigned to the MECH craft. | I17: Start Center; Result Set | K17: Beginner | M17: IBM Docs > Maximo Manage > Administering > Organizations and sites | N17: Drafted | Q17: query-saved-query
A18: M01-017 | B18: 01 Foundations and Structure | C18: Record basics | D18: Start Center | F18: The home page a user sees after logging in. It is made of portlets like result sets, KPIs, bulletin board messages and quick links, and it is assigned through security groups. | G18: Start Center (home page); Start Center Templates | H18: Planners at RWA see their backlog, overdue PMs and a KPI for schedule compliance as soon as they log in. | I18: Result Set; KPI (Key Performance Indicator); Security Group; Work Center | K18: Beginner | M18: IBM Docs > Maximo Manage > Administering > Organizations and sites | N18: Drafted | Q18: start-center
A19: M01-018 | B19: 01 Foundations and Structure | C19: Record basics | D19: Work Center | F19: A simplified, role-focused screen in Maximo designed for specific jobs like technician, supervisor or inventory clerk. Work Centers were the first step toward the newer role-based applications. | G19: Work Centers (from Start Center) | I19: Role-based Application; Start Center | K19: Intermediate | L19: Introduced in later 7.6 releases. In MAS, role-based applications built on the Maximo Application Framework carry this idea forward. | M19: IBM Docs > Maximo Manage > Administering > Organizations and sites | N19: Drafted | Q19: work-center
A20: M01-019 | B20: 01 Foundations and Structure | C20: Record basics | D20: Bulletin Board | F20: A place for posting announcements that show on users' Start Centers, targeted by site, organization or person group. | G20: Bulletin Board app | H20: RWA posts 'Intake channel closed for inspection Monday' to all TP1 users. | I20: Start Center; Communication Template | K20: Beginner | M20: IBM Docs > Maximo Manage > Administering > Organizations and sites | N20: Drafted | Q20: bulletin-board
A21: M02-001 | B21: 02 Assets and Locations | C21: Locations | D21: Location | E21: LOCATION | F21: A place where an asset sits or work happens, defined by its function rather than the equipment in it. A location stays the same even when the asset inside it gets swapped out. | G21: Locations app | H21: TP1-INTAKE-PS is the raw water intake pump position. The pump in it can change; the position does not. | I21: Asset; Location Hierarchy; System (Location System); Location Type | J21: The classic mix-up: a location is the job the equipment does or the spot it lives in, while an asset is the physical thing you can pick up and move. | K21: Beginner | M21: IBM Docs > Maximo Manage > Assets / Locations | N21: Drafted | Q21: location
A22: M02-002 | B22: 02 Assets and Locations | C22: Locations | D22: Location Type | E22: TYPE | F22: A setting that tells Maximo what a location is used for. Common types include OPERATING, STOREROOM, REPAIR, SALVAGE, VENDOR, COURIER and LABOR. | G22: Locations app (Type field) | H22: CENTRAL is a STOREROOM location, TP1-INTAKE-PS is an OPERATING location and REPAIR-SHOP is a REPAIR location. | I22: Location; Storeroom; Repair Facility | K22: Intermediate | M22: IBM Docs > Maximo Manage > Assets / Locations | N22: Drafted | Q22: location-type
A23: M02-003 | B23: 02 Assets and Locations | C23: Locations | D23: Location Hierarchy | F23: The parent and child structure of locations that shows how places are organized, from a whole site down to individual equipment positions. | G23: Locations app, Systems section | H23: TP1 > TP1-INTAKE > TP1-INTAKE-PS > P-101 position. | I23: System (Location System); Primary System; Asset Hierarchy | K23: Beginner | M23: IBM Docs > Maximo Manage > Assets / Locations | N23: Drafted | Q23: location-hierarchy
A24: M02-004 | B24: 02 Assets and Locations | C24: Locations | D24: System (Location System) | E24: SYSTEMID | F24: A named hierarchy that locations belong to. One location can belong to several systems, which lets you view the same places from different angles, such as by process or by electrical feed. | G24: Locations app; Systems action | H24: TP1 has a PROCESS system that follows how water flows and an ELECTRICAL system that follows the power feeds. | I24: Location Hierarchy; Primary System; Network (Location Network) | K24: Intermediate | M24: IBM Docs > Maximo Manage > Assets / Locations | N24: Drafted | Q24: system-location-system
A25: M02-005 | B25: 02 Assets and Locations | C25: Locations | D25: Primary System | F25: The main location hierarchy for a site. Each site has exactly one, and it is the default view of where everything fits. | G25: Locations app (System field marked Primary) | H25: PROCESS is RWA TP1's primary system. | I25: System (Location System); Location Hierarchy | K25: Intermediate | M25: IBM Docs > Maximo Manage > Assets / Locations | N25: Drafted | Q25: primary-system
A26: M02-006 | B26: 02 Assets and Locations | C26: Locations | D26: Network (Location Network) | F26: A type of location system where a location can have more than one parent, useful for pipe networks or utilities where things connect in more than one direction. | G26: Locations app (Network systems) | H26: The DIST water main network lets a valve connect to two upstream mains. | I26: System (Location System); Linear Asset | K26: Advanced | M26: IBM Docs > Maximo Manage > Assets / Locations | N26: Drafted | Q26: network-location-network
A27: M02-007 | B27: 02 Assets and Locations | C27: Locations | D27: Repair Facility | F27: A location of type REPAIR where broken rotating assets are sent to be fixed. Work orders can be raised against the repair facility. | G27: Locations app; Work Order Tracking (Repair Facility field) | H27: A failed motor is moved to REPAIR-SHOP, rebuilt, then returned to the CENTRAL storeroom. | I27: Rotating Asset / Rotating Item; Location Type | K27: Advanced | M27: IBM Docs > Maximo Manage > Assets / Locations | N27: Drafted | Q27: repair-facility
A28: M02-008 | B28: 02 Assets and Locations | C28: Assets | D28: Asset | E28: ASSETNUM | F28: A physical piece of equipment or property that you want to track, maintain and cost, like a pump, motor, vehicle or HVAC unit. Each asset has its own history of work, costs, meters and failures. | G28: Assets app | H28: P-101 is a 250 HP centrifugal raw water pump. All of its repairs, PMs and costs roll up to this record. | I28: Location; Asset Hierarchy; Rotating Asset / Rotating Item; Asset Status | J28: Not everything needs to be an asset. If you will never maintain, cost or report on it individually, tracking it as an asset just adds noise. | K28: Beginner | M28: IBM Docs > Maximo Manage > Assets / Locations | N28: Drafted | Q28: asset
A29: M02-009 | B29: 02 Assets and Locations | C29: Assets | D29: Asset Hierarchy | E29: PARENT | F29: The parent and child relationships between assets, showing what is part of what. Costs can roll up from children to parents. | G29: Assets app (Parent field; Children view) | H29: P-101 (pump) is the parent of M-101 (motor) and C-101 (coupling). | I29: Location Hierarchy; Rolled-up Costs; Asset | J29: An asset hierarchy and a location hierarchy are separate structures. Many sites build both, and they often look similar but serve different purposes. | K29: Beginner | M29: IBM Docs > Maximo Manage > Assets / Locations | N29: Drafted | Q29: asset-hierarchy
A30: M02-010 | B30: 02 Assets and Locations | C30: Assets | D30: Asset Status | E30: STATUS | F30: The current state of an asset. Common out-of-the-box values include NOT READY, OPERATING and DECOMMISSIONED, and organizations often add synonyms for their own needs. | G30: Assets app, Change Status action | H30: When P-101 is installed and commissioned, it moves from NOT READY to OPERATING. | I30: Asset Downtime; Status | J30: An asset can be OPERATING while it is down for a repair. Whether it is running right now is tracked separately through downtime reporting. | K30: Beginner | M30: IBM Docs > Maximo Manage > Assets / Locations | N30: Drafted | Q30: asset-status
A31: M02-011 | B31: 02 Assets and Locations | C31: Assets | D31: Rotating Asset / Rotating Item | E31: ROTATING | F31: An item that is stocked in a storeroom but also tracked individually as an asset with its own number and history, because it gets installed, removed, repaired and reused. | G31: Item Master (Rotating checkbox); Assets app | H31: Motor M-101 is a rotating item. When it fails it goes to repair, and a spare motor from CENTRAL is installed in its place, each keeping its own history. | I31: Item Master; Condition Code; Repair Facility; Move / Swap / Modify Assets | J31: Rotating assets are counted in both the asset register and inventory balances, which surprises people the first time they reconcile numbers. | K31: Intermediate | M31: IBM Docs > Maximo Manage > Assets / Locations | N31: Drafted | Q31: rotating-asset-rotating-item
A32: M02-012 | B32: 02 Assets and Locations | C32: Assets | D32: Move / Swap / Modify Assets | F32: Actions for moving an asset to another location, swapping one asset for another, or changing its details while keeping its history. | G32: Assets app, Move/Modify Assets and Swap Asset actions | H32: Mechanics swap failed motor M-101 with spare M-117. Maximo records both moves and the date of each. | I32: Rotating Asset / Rotating Item; Asset Status | K32: Intermediate | M32: IBM Docs > Maximo Manage > Assets / Locations | N32: Drafted | Q32: move-swap-modify-assets
A33: M02-013 | B33: 02 Assets and Locations | C33: Assets | D33: Spare Parts (Asset) | F33: A list of items linked to an asset showing which parts are used to maintain it. It helps planners and technicians know exactly what to pull from stores. | G33: Assets app, Spare Parts tab | H33: P-101's spare parts list includes seal kit 1001-SEAL, bearing 2040 and coupling insert 3310. | I33: Item Master; Job Plan Materials / Labor / Services / Tools | K33: Beginner | M33: IBM Docs > Maximo Manage > Assets / Locations | N33: Drafted | Q33: spare-parts-asset
A34: M02-014 | B34: 02 Assets and Locations | C34: Assets | D34: Asset Specifications | F34: Technical attributes stored on an asset, such as horsepower, voltage or flow rate, usually driven by its classification. | G34: Assets app, Specifications tab | H34: P-101's specs show 250 HP, 600 V and a rated flow of 900 m3/h. | I34: Classification; Attribute | K34: Intermediate | M34: IBM Docs > Maximo Manage > Assets / Locations | N34: Drafted | Q34: asset-specifications
A35: M02-015 | B35: 02 Assets and Locations | C35: Assets | D35: Asset Template | F35: A reusable pattern for creating many similar assets with the same specs, spare parts, meters, PMs and other details. | G35: Asset Templates app | H35: RWA builds a template for its standard 40 HP booster pump and creates 12 identical assets for DIST pump stations in one pass. | I35: Asset; Classification; Preventive Maintenance (PM) Record | K35: Intermediate | M35: IBM Docs > Maximo Manage > Assets / Locations | N35: Drafted | Q35: asset-template
A36: M02-016 | B36: 02 Assets and Locations | C36: Assets | D36: Asset Downtime | F36: A record of when an asset was not available, captured by reporting it down and back up. Downtime history feeds availability and reliability reporting. | G36: Assets app or Work Order Tracking, Report Downtime action | H36: P-101 is reported down at 08:15 for the seal repair and back up at 14:40, logging 6.4 hours of downtime. | I36: Availability; MTTR (Mean Time to Repair); Asset Status | K36: Intermediate | M36: IBM Docs > Maximo Manage > Assets / Locations | N36: Drafted | Q36: asset-downtime
A37: M02-017 | B37: 02 Assets and Locations | C37: Assets | D37: Rolled-up Costs | F37: Maintenance costs from child assets and work orders that add up into the parent asset, so you can see the full cost of a system. | G37: Assets app (Cost section; rollup) | H37: Repairs to M-101 and C-101 roll up into P-101's total maintenance cost. | I37: Asset Hierarchy; Planned vs Actual Cost | K37: Intermediate | M37: IBM Docs > Maximo Manage > Assets / Locations | N37: Drafted | Q37: rolled-up-costs
A38: M02-018 | B38: 02 Assets and Locations | C38: Assets | D38: Asset Priority / Criticality | E38: PRIORITY | F38: A rating that shows how important an asset is to operations. It is often used with work order priority to decide what gets done first. | G38: Assets app (Priority field); Maximo Health criticality | H38: P-101 is priority 1 because the plant cannot take in raw water without it. An office HVAC unit is priority 4. | I38: Work Order Priority; Calculated Priority; Criticality Analysis | K38: Beginner | M38: IBM Docs > Maximo Manage > Assets / Locations | N38: Drafted | Q38: asset-priority-criticality
A39: M02-019 | B39: 02 Assets and Locations | C39: Assets | D39: Warranty | F39: Coverage information tied to an asset showing that repairs may be paid for by a vendor. Maximo can warn users when they create work on an asset under warranty. | G39: Assets app; Warranty Contracts app | H39: New motor M-117 is under a two-year manufacturer warranty, so a warning pops up when a work order is created on it. | I39: Warranty Contract; Purchase Contract | K39: Intermediate | M39: IBM Docs > Maximo Manage > Assets / Locations | N39: Drafted | Q39: warranty
A40: M02-020 | B40: 02 Assets and Locations | C40: Assets | D40: Collection | F40: A named group of assets, locations and other records, often used to control which records a group of users can see or work on. | G40: Collections app | H40: The 'DIST pump stations' collection is used to give the distribution crew access to just their equipment. | I40: Security Group; Asset; Location | K40: Advanced | M40: IBM Docs > Maximo Manage > Assets / Locations | N40: Drafted | Q40: collection
A41: M02-021 | B41: 02 Assets and Locations | C41: Assets | D41: Linear Asset | F41: An asset that is measured along its length, such as a pipeline, road or rail line. Work and features are located by start and end measurements instead of one point. | G41: Assets app with Maximo Linear capabilities | H41: Water main WM-0450 runs 2.3 km. A leak repair is recorded from 1.12 km to 1.15 km. | I41: Network (Location Network); Maximo Spatial | K41: Advanced | M41: IBM Docs > Maximo Manage > Assets / Locations | N41: Drafted | Q41: linear-asset
A42: M02-022 | B42: 02 Assets and Locations | C42: Classifications | D42: Classification | E42: CLASSSTRUCTUREID | F42: A way of categorizing records into a hierarchy, such as PUMP > CENTRIFUGAL. Each class can carry its own set of attributes so similar things are described the same way. | G42: Classifications app | H42: P-101 is classified as PUMP \ CENTRIFUGAL \ HORIZONTAL SPLIT CASE, which brings in attributes like HP, flow and head. | I42: Attribute; Asset Specifications | J42: Good classifications are what make reporting work later. Skipping them early on is one of the most common data quality regrets. | K42: Intermediate | M42: IBM Docs > Maximo Manage > Assets / Locations | N42: Drafted | Q42: classification
A43: M02-023 | B43: 02 Assets and Locations | C43: Classifications | D43: Attribute | E43: ASSETATTRID | F43: A single characteristic, like horsepower or voltage, defined once and reused across classifications and records. | G43: Attributes app; Classifications app | H43: The attribute RATED_HP is used on pumps, motors and blowers. | I43: Classification; Asset Specifications | K43: Intermediate | M43: IBM Docs > Maximo Manage > Assets / Locations | N43: Drafted | Q43: attribute
A44: M02-024 | B44: 02 Assets and Locations | C44: Failure reporting | D44: Failure Code / Failure Class | E44: FAILURECODE | F44: A structured hierarchy used to record why something failed. It runs from failure class to problem to cause to remedy. | G44: Failure Codes app; Work Order Tracking, Failure Reporting tab | H44: PUMPS (class) > LEAKING (problem) > SEAL WORN (cause) > REPLACE SEAL (remedy). | I44: Problem / Cause / Remedy; Reliability-Centered Maintenance (RCM); MTBF (Mean Time Between Failures) | J44: Free-text explanations do not count. Without consistent failure codes, nobody can trend failures later. | K44: Intermediate | M44: IBM Docs > Maximo Manage > Assets / Locations | N44: Drafted | Q44: failure-code-failure-class
A45: M02-025 | B45: 02 Assets and Locations | C45: Failure reporting | D45: Problem / Cause / Remedy | F45: The three levels below a failure class. Problem is what was observed, cause is why it happened and remedy is what fixed it. | G45: Work Order Tracking, Failure Reporting tab | H45: Problem: LEAKING. Cause: SEAL WORN. Remedy: REPLACE SEAL. | I45: Failure Code / Failure Class | K45: Intermediate | M45: IBM Docs > Maximo Manage > Assets / Locations | N45: Drafted | Q45: problem-cause-remedy
A46: M02-026 | B46: 02 Assets and Locations | C46: Meters | D46: Meter | E46: METERNAME | F46: A defined measurement that can be attached to assets or locations to record usage or condition over time. | G46: Meters app; Assets app, Meters tab | H46: P-101 has meters for RUNHOURS, VIBRATION and OIL-CONDITION. | I46: Meter Reading; Meter-based Frequency; Condition Monitoring / Measurement Point | K46: Beginner | M46: IBM Docs > Maximo Manage > Assets / Locations | N46: Drafted | Q46: meter
A47: M02-027 | B47: 02 Assets and Locations | C47: Meters | D47: Meter Type: Continuous / Gauge / Characteristic | E47: METERTYPE | F47: Continuous meters count upward over time (run hours, km). Gauge meters measure a level that goes up and down (temperature, pressure, vibration). Characteristic meters record a value from a list (oil color: CLEAR, CLOUDY, DARK). | G47: Meters app (Meter Type) | H47: RUNHOURS is continuous, VIBRATION is gauge and OIL-CONDITION is characteristic. | I47: Meter; Meter Reading | J47: Only continuous meters can trigger usage-based PMs. Gauge and characteristic readings drive condition monitoring instead. | K47: Intermediate | M47: IBM Docs > Maximo Manage > Assets / Locations | N47: Drafted | Q47: meter-type-continuous-gauge-characteristic
A48: M02-028 | B48: 02 Assets and Locations | C48: Meters | D48: Meter Group | F48: A set of meters bundled together so they can be added to an asset in one step. | G48: Meter Groups app | H48: The PUMP-STD meter group adds RUNHOURS, VIBRATION and BEARING-TEMP to every new pump. | I48: Meter; Asset Template | K48: Intermediate | M48: IBM Docs > Maximo Manage > Assets / Locations | N48: Drafted | Q48: meter-group
A49: M02-029 | B49: 02 Assets and Locations | C49: Meters | D49: Meter Reading | F49: A single value entered or received for a meter at a point in time. Readings can be entered manually, on a work order or through integration. | G49: Assets app, Enter Meter Readings action; Maximo Mobile | H49: An operator enters 14,212 run hours for P-101 on Monday's round. | I49: Meter | K49: Beginner | M49: IBM Docs > Maximo Manage > Assets / Locations | N49: Drafted | Q49: meter-reading
A50: M02-030 | B50: 02 Assets and Locations | C50: Meters | D50: Condition Monitoring / Measurement Point | E50: POINTNUM | F50: Setting upper and lower limits on gauge or characteristic readings so that Maximo creates a work order when a value goes out of range. | G50: Condition Monitoring app | H50: If P-101 vibration exceeds 7.1 mm/s, Maximo automatically raises an inspection work order. | I50: Meter Type: Continuous / Gauge / Characteristic; Condition-based Maintenance (CBM); Maximo Monitor | K50: Intermediate | M50: IBM Docs > Maximo Manage > Assets / Locations | N50: Drafted | Q50: condition-monitoring-measurement-point
A51: M03-001 | B51: 03 Work Management | C51: Requests | D51: Service Request | E51: SR | F51: A request from anyone in the organization saying something needs attention. A service request is not yet approved work; it gets reviewed and, if valid, turned into a work order. | G51: Service Requests app; Create Service Request (self-service) | H51: An operator notices water pooling under P-101 and submits a service request from her phone. | I51: Work Order; Ticket Template; Self-Service Request | J51: Service requests and work orders are not the same thing. A request is someone asking; a work order is the business agreeing to do the work. | K51: Beginner | M51: IBM Docs > Maximo Manage > Work management | N51: Drafted | Q51: service-request
A52: M03-002 | B52: 03 Work Management | C52: Requests | D52: Self-Service Request | F52: A simplified screen where people without full Maximo training can submit and track their own requests. | G52: Create Service Request and View Service Requests apps | H52: An office worker at head office reports a broken door lock without learning the full Service Requests app. | I52: Service Request | K52: Beginner | M52: IBM Docs > Maximo Manage > Work management | N52: Drafted | Q52: self-service-request
A53: M03-003 | B53: 03 Work Management | C53: Requests | D53: Ticket Template | F53: A preset that fills in common details on service requests or incidents, such as classification, owner group and description. | G53: Ticket Templates app | H53: A 'Water leak' template fills in classification LEAK, owner group TP1-SUPV and priority 2. | I53: Service Request; Classification | K53: Intermediate | M53: IBM Docs > Maximo Manage > Work management | N53: Drafted | Q53: ticket-template
A54: M03-004 | B54: 03 Work Management | C54: Work orders | D54: Work Order | E54: WONUM | F54: The record that authorizes, plans, tracks and costs a piece of maintenance work. It holds what needs doing, on which asset or location, who does it, what parts and tools are needed and what it actually cost. | G54: Work Order Tracking app | H54: Work order 50231: replace mechanical seal on P-101, priority 1, MECH craft, 4 planned hours. | I54: Work Order Lifecycle / Status Flow; Job Plan; Plans Tab (Planned Work); Actuals Tab; Work Type | K54: Beginner | M54: IBM Docs > Maximo Manage > Work management | N54: Drafted | Q54: work-order
A55: M03-005 | B55: 03 Work Management | C55: Work orders | D55: Work Order Lifecycle / Status Flow | E55: WOSTATUS | F55: The path a work order follows from creation to closure. A common flow is WAPPR (waiting on approval) > APPR (approved) > INPRG (in progress) > COMP (complete) > CLOSE (closed). Other common values include WMATL (waiting on material), WSCH (waiting to be scheduled), WPCOND (waiting on plant conditions) and CAN (cancelled). | G55: Work Order Tracking, Change Status action | H55: WO 50231 is created WAPPR, approved APPR, goes WMATL until the seal kit arrives, then INPRG, COMP and finally CLOSE. | I55: Status; Synonym Domain; Work Order | J55: COMP and CLOSE are not the same. COMP means the work is done; CLOSE locks the record so costs and details can no longer change. | K55: Beginner | M55: IBM Docs > Maximo Manage > Work management | N55: Drafted | Q55: work-order-lifecycle-status-flow
A56: M03-006 | B56: 03 Work Management | C56: Work orders | D56: Work Type | E56: WORKTYPE | F56: A code that classifies the kind of work. Common examples are CM (corrective), PM (preventive), EM (emergency), CP (capital project) and EV (event). Each organization usually adjusts this list. | G56: Work Types (Organizations app); Work Order Tracking | H56: The seal replacement is CM. The quarterly pump inspection is PM. | I56: Work Order; Preventive Maintenance (PM) Record; KPI (Key Performance Indicator) | J56: Work type is how you later measure your planned vs reactive ratio, so inconsistent use ruins that reporting. | K56: Beginner | M56: IBM Docs > Maximo Manage > Work management | N56: Drafted | Q56: work-type
A57: M03-007 | B57: 03 Work Management | C57: Work orders | D57: Work Order Priority | E57: WOPRIORITY | F57: A number that tells people how urgent the work is. Many organizations combine it with asset priority to calculate an overall priority. | G57: Work Order Tracking (Priority field) | H57: Seal leak WO 50231 is priority 1; repainting the pump room floor is priority 5. | I57: Asset Priority / Criticality; Calculated Priority | K57: Beginner | M57: IBM Docs > Maximo Manage > Work management | N57: Drafted | Q57: work-order-priority
A58: M03-008 | B58: 03 Work Management | C58: Work orders | D58: Calculated Priority | E58: CALCPRIORITY | F58: An overall priority that Maximo can work out by combining work order priority and asset or location priority using a formula you set up. | G58: Organizations app (Work Order Options); Work Order Tracking | H58: WO priority 2 on priority 1 asset P-101 scores higher than WO priority 1 on a priority 5 office fan. | I58: Asset Priority / Criticality; Work Order Priority | K58: Advanced | M58: IBM Docs > Maximo Manage > Work management | N58: Drafted | Q58: calculated-priority
A59: M03-009 | B59: 03 Work Management | C59: Work orders | D59: Plans Tab (Planned Work) | F59: The section of a work order that holds what is expected: tasks, labor, materials, services and tools. Plans are often copied in from a job plan. | G59: Work Order Tracking, Plans tab | H59: WO 50231 plans 1 MECH for 4 hours, one 1001-SEAL kit and a torque wrench. | I59: Job Plan; Actuals Tab; Work Order Estimate / Estimated Cost | K59: Beginner | M59: IBM Docs > Maximo Manage > Work management | N59: Drafted | Q59: plans-tab-planned-work
A60: M03-010 | B60: 03 Work Management | C60: Work orders | D60: Actuals Tab | F60: The section of a work order that records what really happened: labor hours, materials issued, services received and tools used. Actuals drive the real cost of work. | G60: Work Order Tracking, Actuals tab | H60: The mechanic records 5.5 actual hours and one seal kit, so actual cost is higher than the 4 hours planned. | I60: Plans Tab (Planned Work); Labor Reporting; Inventory Usage | K60: Beginner | M60: IBM Docs > Maximo Manage > Work management | N60: Drafted | Q60: actuals-tab
A61: M03-011 | B61: 03 Work Management | C61: Work orders | D61: Task (Work Order Task) | E61: TASKID | F61: A step inside a work order. Tasks can have their own status, labor and materials, and can be linked so one must finish before another starts. | G61: Work Order Tracking, Plans tab, Tasks | H61: Task 10: lock out pump. Task 20: drain casing. Task 30: replace seal. Task 40: test and return to service. | I61: Job Plan; Child Work Order / Work Package | K61: Beginner | M61: IBM Docs > Maximo Manage > Work management | N61: Drafted | Q61: task-work-order-task
A62: M03-012 | B62: 03 Work Management | C62: Work orders | D62: Child Work Order / Work Package | E62: PARENT | F62: A work order that sits under another work order. Parent work orders group related work so it can be planned and costed together. | G62: Work Order Tracking, Plans tab, Children | H62: Parent WO 50400 'TP1 annual shutdown' has 37 child work orders under it. | I62: Task (Work Order Task) | K62: Intermediate | M62: IBM Docs > Maximo Manage > Work management | N62: Drafted | Q62: child-work-order-work-package
A63: M03-013 | B63: 03 Work Management | C63: Work orders | D63: Follow-up Work Order | F63: A new work order created from an existing one when a technician finds more work that needs doing later. | G63: Work Order Tracking, Create > Follow-up Work Order | H63: During the seal job, the mechanic sees corrosion on the baseplate and raises follow-up WO 50238. | I63: Related Records; Work Order | K63: Beginner | M63: IBM Docs > Maximo Manage > Work management | N63: Drafted | Q63: follow-up-work-order
A64: M03-014 | B64: 03 Work Management | C64: Work orders | D64: Related Records | F64: Links between work orders, service requests and other tickets so people can see how pieces of work connect. | G64: Related Records tab | H64: SR 3412 (water pooling) is related to WO 50231 (seal replacement) and follow-up WO 50238. | I64: Service Request; Follow-up Work Order | K64: Beginner | M64: IBM Docs > Maximo Manage > Work management | N64: Drafted | Q64: related-records
A65: M03-015 | B65: 03 Work Management | C65: Work orders | D65: Work Order Estimate / Estimated Cost | F65: The expected cost of a work order based on planned labor, materials, services and tools. Many organizations use it for approval limits. | G65: Work Order Tracking, View Costs action | H65: Estimated cost on WO 50231 is $1,180 and the supervisor's approval limit is $5,000, so he can approve it. | I65: Plans Tab (Planned Work); Approval Limit / Tolerance; Planned vs Actual Cost | K65: Intermediate | M65: IBM Docs > Maximo Manage > Work management | N65: Drafted | Q65: work-order-estimate-estimated-cost
A66: M03-016 | B66: 03 Work Management | C66: Work orders | D66: Quick Reporting | F66: A fast way to create and complete simple, unplanned work in one step, recording labor, materials and failure codes together. | G66: Quick Reporting app | H66: A tech tightens a loose guard on P-102, logs 0.5 hours and closes it out in under a minute. | I66: Work Order; Actuals Tab | K66: Beginner | M66: IBM Docs > Maximo Manage > Work management | N66: Drafted | Q66: quick-reporting
A67: M03-017 | B67: 03 Work Management | C67: Work orders | D67: Work Order Status History | F67: A record of every status change on a work order, with who changed it and when. It is useful for audits and measuring things like time to approve. | G67: Work Order Tracking, View Status History | H67: History shows WO 50231 spent 18 hours in WMATL waiting for the seal kit. | I67: Status; KPI (Key Performance Indicator) | K67: Beginner | M67: IBM Docs > Maximo Manage > Work management | N67: Drafted | Q67: work-order-status-history
A68: M03-018 | B68: 03 Work Management | C68: Work orders | D68: Work Order Generated by PM | E68: PMNUM | F68: A work order created automatically from a preventive maintenance record when it comes due. | G68: Work Order Tracking (PM field) | H68: WO 50300 was generated from PM-P101-QTR for P-101's quarterly inspection. | I68: Preventive Maintenance (PM) Record; Job Plan; Work Type | K68: Beginner | M68: IBM Docs > Maximo Manage > Work management | N68: Drafted | Q68: work-order-generated-by-pm
A69: M03-019 | B69: 03 Work Management | C69: Work orders | D69: Emergency Work Order | F69: Unplanned work that has to happen immediately. Often created with a special work type and allowed to skip normal approval steps. | G69: Work Order Tracking (often with Work Type EM) | H69: A main break at DIST gets an EM work order and goes straight to INPRG. | I69: Work Type; Work Order Priority | K69: Beginner | M69: IBM Docs > Maximo Manage > Work management | N69: Drafted | Q69: emergency-work-order
A70: M03-020 | B70: 03 Work Management | C70: Work orders | D70: Work Order Classification | F70: Using classifications on work orders to categorize the type of job, which makes searching and reporting cleaner. | G70: Work Order Tracking (Classification field); Classifications app | H70: WO 50231 is classified MECHANICAL \ SEAL. | I70: Classification; Failure Code / Failure Class | K70: Intermediate | M70: IBM Docs > Maximo Manage > Work management | N70: Drafted | Q70: work-order-classification
A71: M03-021 | B71: 03 Work Management | C71: Work orders | D71: Downtime on Work Order | F71: Reporting an asset down and back up directly from a work order so the outage is tied to the work that caused it. | G71: Work Order Tracking, Report Downtime action | H71: P-101 downtime of 6.4 hours is linked to WO 50231. | I71: Asset Downtime; Availability | K71: Intermediate | M71: IBM Docs > Maximo Manage > Work management | N71: Drafted | Q71: downtime-on-work-order
A72: M03-022 | B72: 03 Work Management | C72: Execution | D72: Labor Reporting | F72: Recording the hours people spent on work orders, either from the work order or in bulk from a separate application. | G72: Labor Reporting app; Work Order Tracking, Actuals tab | H72: A supervisor enters a full day of crew hours across six work orders at once. | I72: Actuals Tab; Labor; Craft; Labor Rate | K72: Beginner | M72: IBM Docs > Maximo Manage > Work management | N72: Drafted | Q72: labor-reporting
A73: M03-023 | B73: 03 Work Management | C73: Execution | D73: Assignment | F73: A link between a person or labor record and a task or work order for a scheduled time. | G73: Assignment Manager; Graphical Assignment | H73: Mechanic Dev Patel is assigned WO 50231 for Tuesday 08:00 to 12:00. | I73: Labor; Planning vs Scheduling; Dispatching | K73: Intermediate | M73: IBM Docs > Maximo Manage > Work management | N73: Drafted | Q73: assignment
A74: M03-024 | B74: 03 Work Management | C74: Execution | D74: Dispatching | F74: Sending scheduled work to the people who will do it, often with the assignments pushed to mobile devices. | G74: Graphical Assignment; Maximo Mobile | H74: Tuesday's assignments are dispatched to each tech's tablet at 06:30. | I74: Assignment; Planning vs Scheduling; Maximo Mobile | K74: Intermediate | M74: IBM Docs > Maximo Manage > Work management | N74: Drafted | Q74: dispatching
A75: M03-025 | B75: 03 Work Management | C75: Execution | D75: Backlog | F75: All approved work that has not been completed yet. Maintenance teams track backlog in weeks of crew capacity to know if they are keeping up. | G75: Work Order Tracking query; Start Center result sets | H75: TP1 has 620 hours of approved MECH backlog and 3 mechanics, so about 5 weeks of backlog. | I75: Planning vs Scheduling; KPI (Key Performance Indicator) | K75: Beginner | M75: IBM Docs > Maximo Manage > Work management | N75: Drafted | Q75: backlog
A76: M03-026 | B76: 03 Work Management | C76: Execution | D76: Inspection | F76: A structured check of an asset or location using a form with questions, readings and photos. Results can create follow-up work. | G76: Inspection Forms; Maximo Mobile Inspections | H76: An operator walks the intake, answering 12 inspection questions and taking a photo of the screen. | I76: Inspection Form; Maximo Mobile; Condition Monitoring / Measurement Point | K76: Beginner | M76: IBM Docs > Maximo Manage > Work management | N76: Drafted | Q76: inspection
A77: M03-027 | B77: 03 Work Management | C77: Execution | D77: Inspection Form | F77: The template for an inspection, made up of questions, response types, meter readings and conditional logic. | G77: Inspection Forms app (MAS) | H77: The 'Daily Intake Round' form has yes/no, numeric and photo questions. | I77: Inspection; Maximo Mobile | K77: Intermediate | L77: Introduced in later 7.6.1 releases and expanded in MAS through Maximo Mobile Inspections. | M77: IBM Docs > Maximo Manage > Work management | N77: Drafted | Q77: inspection-form
A78: M04-001 | B78: 04 Planning: Job Plans, PMs, Routes and Safety | C78: Job plans | D78: Job Plan | E78: JPNUM | F78: A reusable recipe for a type of work. It lists the tasks, labor, materials, services and tools needed, so planners do not rebuild the same plan every time. | G78: Job Plans app | H78: JP-SEAL-CENT is the standard plan for replacing a mechanical seal on a centrifugal pump. | I78: Work Order; Preventive Maintenance (PM) Record; Task (Work Order Task); Nested Job Plan | J78: A job plan is not a schedule. It describes how to do the work; a PM decides when. | K78: Beginner | M78: IBM Docs > Maximo Manage > Planning / Preventive maintenance | N78: Drafted | Q78: job-plan
A79: M04-002 | B79: 04 Planning: Job Plans, PMs, Routes and Safety | C79: Job plans | D79: Job Plan Status | F79: Job plans have statuses such as DRAFT, ACTIVE, INACTIVE and PNDREV (pending revision). Only active job plans can be applied to work orders. | G79: Job Plans app, Change Status | H79: JP-SEAL-CENT is ACTIVE. A new version is being written in PNDREV. | I79: Job Plan Revision | K79: Intermediate | M79: IBM Docs > Maximo Manage > Planning / Preventive maintenance | N79: Drafted | Q79: job-plan-status
A80: M04-003 | B80: 04 Planning: Job Plans, PMs, Routes and Safety | C80: Job plans | D80: Job Plan Revision | F80: Creating a new version of a job plan while keeping the old one, so changes are controlled and history is kept. | G80: Job Plans app, Revise Job Plan action | H80: After a near miss, RWA revises JP-SEAL-CENT to add a second lockout check, creating revision 2. | I80: Job Plan Status | K80: Intermediate | M80: IBM Docs > Maximo Manage > Planning / Preventive maintenance | N80: Drafted | Q80: job-plan-revision
A81: M04-004 | B81: 04 Planning: Job Plans, PMs, Routes and Safety | C81: Job plans | D81: Nested Job Plan | F81: A job plan used as a task inside another job plan, so common steps can be reused. | G81: Job Plans app (Nested Job Plan field on a task) | H81: JP-LOTO-PUMP (lockout steps) is nested inside both JP-SEAL-CENT and JP-BEARING-CENT. | I81: Job Plan; Task (Work Order Task) | K81: Advanced | M81: IBM Docs > Maximo Manage > Planning / Preventive maintenance | N81: Drafted | Q81: nested-job-plan
A82: M04-005 | B82: 04 Planning: Job Plans, PMs, Routes and Safety | C82: Job plans | D82: Job Plan Materials / Labor / Services / Tools | F82: The four kinds of resources a job plan can list. They copy onto the work order's Plans tab when the job plan is applied. | G82: Job Plans app, Labor, Materials, Services and Tools tabs | H82: JP-SEAL-CENT lists 1 MECH for 4 hours, 1 seal kit 1001-SEAL, and a seal installation tool. | I82: Plans Tab (Planned Work); Item; Craft; Tool | K82: Beginner | M82: IBM Docs > Maximo Manage > Planning / Preventive maintenance | N82: Drafted | Q82: job-plan-materials-labor-services-tools
A83: M04-006 | B83: 04 Planning: Job Plans, PMs, Routes and Safety | C83: Preventive maintenance | D83: Preventive Maintenance (PM) Record | E83: PMNUM | F83: A record that automatically creates work orders on a schedule based on time, usage or both. It answers 'when should this work happen?' | G83: Preventive Maintenance app | H83: PM-P101-QTR creates an inspection work order on P-101 every 3 months using JP-INSP-PUMP. | I83: Job Plan; Time-based Frequency; Work Order Generation (PM); Lead Time (PM) | K83: Beginner | M83: IBM Docs > Maximo Manage > Planning / Preventive maintenance | N83: Drafted | Q83: preventive-maintenance-pm-record
A84: M04-007 | B84: 04 Planning: Job Plans, PMs, Routes and Safety | C84: Preventive maintenance | D84: Time-based Frequency | F84: A PM schedule driven by calendar time, such as every 30 days, 3 months or 1 year. | G84: Preventive Maintenance app, Frequency tab | H84: PM-P101-QTR runs every 3 months. | I84: Preventive Maintenance (PM) Record; Meter-based Frequency; Fixed vs Floating Schedule | K84: Beginner | M84: IBM Docs > Maximo Manage > Planning / Preventive maintenance | N84: Drafted | Q84: time-based-frequency
A85: M04-008 | B85: 04 Planning: Job Plans, PMs, Routes and Safety | C85: Preventive maintenance | D85: Meter-based Frequency | F85: A PM schedule driven by usage measured on a continuous meter, such as every 2,000 run hours or 10,000 km. | G85: Preventive Maintenance app, Frequency tab, Meter-based | H85: PM-P101-LUBE triggers every 500 run hours on the RUNHOURS meter. | I85: Meter Type: Continuous / Gauge / Characteristic; Preventive Maintenance (PM) Record | K85: Intermediate | M85: IBM Docs > Maximo Manage > Planning / Preventive maintenance | N85: Drafted | Q85: meter-based-frequency
A86: M04-009 | B86: 04 Planning: Job Plans, PMs, Routes and Safety | C86: Preventive maintenance | D86: Fixed vs Floating Schedule | F86: A fixed schedule keeps the next due date anchored to the original plan no matter when the last job was done. A floating schedule resets from when the last work order was actually completed or started. | G86: Preventive Maintenance app (Use Last Work Order's Start Date to Calculate Next Due Date option) | H86: If quarterly PM work is done two weeks late, a fixed schedule keeps the same next date, while a floating schedule pushes the next one two weeks out. | I86: Preventive Maintenance (PM) Record; Time-based Frequency | J86: Teams often switch to floating without realizing it can quietly reduce how often critical PMs happen. | K86: Intermediate | M86: IBM Docs > Maximo Manage > Planning / Preventive maintenance | N86: Drafted | Q86: fixed-vs-floating-schedule
A87: M04-010 | B87: 04 Planning: Job Plans, PMs, Routes and Safety | C87: Preventive maintenance | D87: Lead Time (PM) | F87: How many days before the due date Maximo should create the work order, giving planners time to get parts and schedule people. | G87: Preventive Maintenance app (Lead Time field) | H87: PM-P101-QTR has a 14-day lead time so planners can schedule around plant operations. | I87: Preventive Maintenance (PM) Record; Work Order Generation (PM) | K87: Beginner | M87: IBM Docs > Maximo Manage > Planning / Preventive maintenance | N87: Drafted | Q87: lead-time-pm
A88: M04-011 | B88: 04 Planning: Job Plans, PMs, Routes and Safety | C88: Preventive maintenance | D88: Work Order Generation (PM) | F88: The process of creating work orders from PM records, either manually or through a scheduled cron task that runs automatically. | G88: Preventive Maintenance app, Generate Work Orders action; Cron Task Setup (PM work order generation cron task) | H88: Every night, the PM cron task checks all active PMs and creates work orders for any coming due. | I88: Cron Task; Preventive Maintenance (PM) Record; Lead Time (PM) | K88: Intermediate | M88: IBM Docs > Maximo Manage > Planning / Preventive maintenance | N88: Drafted | Q88: work-order-generation-pm
A89: M04-012 | B89: 04 Planning: Job Plans, PMs, Routes and Safety | C89: Preventive maintenance | D89: Job Plan Sequence | F89: A PM setting that uses different job plans at different intervals, such as a basic check monthly and a full overhaul every twelfth time. | G89: Preventive Maintenance app, Job Plan Sequence tab | H89: PM-P101-QTR uses JP-INSP-PUMP normally, and JP-OVERHAUL-PUMP every 4th time (once a year). | I89: Preventive Maintenance (PM) Record; Job Plan | K89: Advanced | M89: IBM Docs > Maximo Manage > Planning / Preventive maintenance | N89: Drafted | Q89: job-plan-sequence
A90: M04-013 | B90: 04 Planning: Job Plans, PMs, Routes and Safety | C90: Preventive maintenance | D90: PM Hierarchy | F90: Parent and child PMs that generate work together, so a large job made of several pieces comes out as one package. | G90: Preventive Maintenance app, PM Hierarchy tab | H90: An annual shutdown PM at TP1 generates a parent work order with child work orders for each pump, valve and motor. | I90: Child Work Order / Work Package; Preventive Maintenance (PM) Record | K90: Advanced | M90: IBM Docs > Maximo Manage > Planning / Preventive maintenance | N90: Drafted | Q90: pm-hierarchy
A91: M04-014 | B91: 04 Planning: Job Plans, PMs, Routes and Safety | C91: Preventive maintenance | D91: Master PM | F91: A template PM used to create and update many regular PMs for similar assets at once. | G91: Master PM app | H91: Master PM MPM-BOOSTER-ANN keeps 12 booster pump PMs in line; one change updates them all. | I91: Preventive Maintenance (PM) Record; Asset Template | K91: Advanced | M91: IBM Docs > Maximo Manage > Planning / Preventive maintenance | N91: Drafted | Q91: master-pm
A92: M04-015 | B92: 04 Planning: Job Plans, PMs, Routes and Safety | C92: Preventive maintenance | D92: Seasonal Dates | F92: Settings that only allow PM work orders to be generated during certain months or days. | G92: Preventive Maintenance app, Seasonal Dates tab | H92: Hydrant flushing PMs only generate between May and October. | I92: Preventive Maintenance (PM) Record; Time-based Frequency | K92: Intermediate | M92: IBM Docs > Maximo Manage > Planning / Preventive maintenance | N92: Drafted | Q92: seasonal-dates
A93: M04-016 | B93: 04 Planning: Job Plans, PMs, Routes and Safety | C93: Preventive maintenance | D93: PM Forecast | F93: A projection of when future PM work orders will come due, used to plan labor and budget ahead. | G93: Preventive Maintenance app, Forecast tab / Generate Forecast | H93: The forecast shows TP1 will need about 1,100 PM labor hours next year. | I93: Preventive Maintenance (PM) Record; Budget Monitoring; Planning vs Scheduling | K93: Intermediate | M93: IBM Docs > Maximo Manage > Planning / Preventive maintenance | N93: Drafted | Q93: pm-forecast
A94: M04-017 | B94: 04 Planning: Job Plans, PMs, Routes and Safety | C94: Routes | D94: Route | E94: ROUTE | F94: A list of assets or locations (route stops) to visit in order, often for inspections or rounds. A route can create one work order, or a parent with children or tasks for each stop. | G94: Routes app | H94: Route RT-TP1-DAILY covers the intake, filters, chemical feed and clearwell. | I94: Route Stop; Preventive Maintenance (PM) Record; Inspection | K94: Intermediate | M94: IBM Docs > Maximo Manage > Planning / Preventive maintenance | N94: Drafted | Q94: route
A95: M04-018 | B95: 04 Planning: Job Plans, PMs, Routes and Safety | C95: Routes | D95: Route Stop | F95: One asset or location on a route, optionally with its own job plan. | G95: Routes app, Route Stops tab | H95: Stop 30 on RT-TP1-DAILY is CL2-AN-01, the chlorine analyzer. | I95: Route | K95: Intermediate | M95: IBM Docs > Maximo Manage > Planning / Preventive maintenance | N95: Drafted | Q95: route-stop
A96: M04-019 | B96: 04 Planning: Job Plans, PMs, Routes and Safety | C96: Safety | D96: Safety Plan | F96: A collection of hazards, precautions, lockout/tagout procedures and hazardous materials that apply to a job. It is attached to work orders so safety information goes with the work. | G96: Safety Plans app; Work Order Tracking, Safety Plan tab | H96: Safety plan SP-PUMP-LOTO covers rotating equipment, stored energy and confined space hazards for pump jobs. | I96: Hazard; Precaution; Lockout/Tagout (LOTO) | K96: Intermediate | M96: IBM Docs > Maximo Manage > Planning / Preventive maintenance | N96: Drafted | Q96: safety-plan
A97: M04-020 | B97: 04 Planning: Job Plans, PMs, Routes and Safety | C97: Safety | D97: Hazard | F97: A recorded danger such as electrical energy, chemical exposure or confined space, linked to assets, locations and safety plans. | G97: Hazards app | H97: Hazard CHLORINE-GAS is linked to TP1-CHEM. | I97: Precaution; Safety Plan | K97: Beginner | M97: IBM Docs > Maximo Manage > Planning / Preventive maintenance | N97: Drafted | Q97: hazard
A98: M04-021 | B98: 04 Planning: Job Plans, PMs, Routes and Safety | C98: Safety | D98: Precaution | F98: A protective step or piece of equipment needed to deal with a hazard, such as gloves, a respirator or a gas detector. | G98: Precautions app | H98: For CHLORINE-GAS, the precaution is 'wear SCBA and carry personal gas monitor'. | I98: Hazard; Safety Plan | K98: Beginner | M98: IBM Docs > Maximo Manage > Planning / Preventive maintenance | N98: Drafted | Q98: precaution
A99: M04-022 | B99: 04 Planning: Job Plans, PMs, Routes and Safety | C99: Safety | D99: Lockout/Tagout (LOTO) | F99: The steps used to isolate energy sources and tag them so equipment cannot be started while someone is working on it. | G99: Lock Out / Tag Out app; Safety Plans | H99: Before seal work on P-101, breaker MCC-3-07 is locked out and tagged with Dev's tag. | I99: Safety Plan; Permit to Work | K99: Beginner | M99: IBM Docs > Maximo Manage > Planning / Preventive maintenance | N99: Drafted | Q99: lockout-tagout-loto
A100: M04-023 | B100: 04 Planning: Job Plans, PMs, Routes and Safety | C100: Safety | D100: Permit to Work | F100: A formal approval that dangerous work can go ahead under certain controls, like hot work or confined space entry. | G100: Work permit capabilities (Health, Safety and Environment add-on in MAS) | H100: Welding near the clearwell requires a hot work permit signed by the shift supervisor. | I100: Lockout/Tagout (LOTO); Health, Safety and Environment (HSE) | K100: Intermediate | L100: Full permit-to-work processes are part of the HSE add-on; base Manage covers simpler safety data. | M100: IBM Docs > Maximo Manage > Planning / Preventive maintenance | N100: Drafted | Q100: permit-to-work
...

Sheet Modules
A1: Module | B1: What it covers | C1: Terms | D1: Beginner | E1: Intermediate | F1: Advanced | G1: Verified or Published | H1: % Verified
A2: 01 Foundations and Structure | B2: How Maximo is organized (organizations, sites, sets) and the basics every screen shares: records, statuses, queries, Start Centers. | C2: =COUNTIF('Term Map'!$B$2:$B$319,A2) -> 19 | D2: =COUNTIFS('Term Map'!$B$2:$B$319,A2,'Term Map'!$K$2:$K$319,"Beginner") -> 13 | E2: =COUNTIFS('Term Map'!$B$2:$B$319,A2,'Term Map'!$K$2:$K$319,"Intermediate") -> 5 | F2: =COUNTIFS('Term Map'!$B$2:$B$319,A2,'Term Map'!$K$2:$K$319,"Advanced") -> 1 | G2: =COUNTIFS('Term Map'!$B$2:$B$319,A2,'Term Map'!$N$2:$N$319,"Verified")+COUNTIFS('Term Map'!$B$2:$B$319,A2,'Term Map'!$N$2:$N$319,"Published") -> 0 | H2: =IFERROR(G2/C2,0) -> 0
A3: 02 Assets and Locations | B3: Locations vs assets, hierarchies, systems, rotating assets, classifications, failure codes and meters. | C3: =COUNTIF('Term Map'!$B$2:$B$319,A3) -> 30 | D3: =COUNTIFS('Term Map'!$B$2:$B$319,A3,'Term Map'!$K$2:$K$319,"Beginner") -> 9 | E3: =COUNTIFS('Term Map'!$B$2:$B$319,A3,'Term Map'!$K$2:$K$319,"Intermediate") -> 17 | F3: =COUNTIFS('Term Map'!$B$2:$B$319,A3,'Term Map'!$K$2:$K$319,"Advanced") -> 4 | G3: =COUNTIFS('Term Map'!$B$2:$B$319,A3,'Term Map'!$N$2:$N$319,"Verified")+COUNTIFS('Term Map'!$B$2:$B$319,A3,'Term Map'!$N$2:$N$319,"Published") -> 0 | H3: =IFERROR(G3/C3,0) -> 0
A4: 03 Work Management | B4: Service requests, work orders, the status lifecycle, plans vs actuals, tasks, child work orders, execution and inspections. | C4: =COUNTIF('Term Map'!$B$2:$B$319,A4) -> 27 | D4: =COUNTIFS('Term Map'!$B$2:$B$319,A4,'Term Map'!$K$2:$K$319,"Beginner") -> 18 | E4: =COUNTIFS('Term Map'!$B$2:$B$319,A4,'Term Map'!$K$2:$K$319,"Intermediate") -> 8 | F4: =COUNTIFS('Term Map'!$B$2:$B$319,A4,'Term Map'!$K$2:$K$319,"Advanced") -> 1 | G4: =COUNTIFS('Term Map'!$B$2:$B$319,A4,'Term Map'!$N$2:$N$319,"Verified")+COUNTIFS('Term Map'!$B$2:$B$319,A4,'Term Map'!$N$2:$N$319,"Published") -> 0 | H4: =IFERROR(G4/C4,0) -> 0
A5: 04 Planning: Job Plans, PMs, Routes and Safety | B5: Job plans, preventive maintenance schedules, routes and safety (hazards, precautions, lockout/tagout, permits). | C5: =COUNTIF('Term Map'!$B$2:$B$319,A5) -> 23 | D5: =COUNTIFS('Term Map'!$B$2:$B$319,A5,'Term Map'!$K$2:$K$319,"Beginner") -> 8 | E5: =COUNTIFS('Term Map'!$B$2:$B$319,A5,'Term Map'!$K$2:$K$319,"Intermediate") -> 11 | F5: =COUNTIFS('Term Map'!$B$2:$B$319,A5,'Term Map'!$K$2:$K$319,"Advanced") -> 4 | G5: =COUNTIFS('Term Map'!$B$2:$B$319,A5,'Term Map'!$N$2:$N$319,"Verified")+COUNTIFS('Term Map'!$B$2:$B$319,A5,'Term Map'!$N$2:$N$319,"Published") -> 0 | H5: =IFERROR(G5/C5,0) -> 0
A6: 05 Inventory and Storerooms | B6: Items, storerooms, balances, reservations, issues, returns, transfers, counting, reordering and cost types. | C6: =COUNTIF('Term Map'!$B$2:$B$319,A6) -> 30 | D6: =COUNTIFS('Term Map'!$B$2:$B$319,A6,'Term Map'!$K$2:$K$319,"Beginner") -> 9 | E6: =COUNTIFS('Term Map'!$B$2:$B$319,A6,'Term Map'!$K$2:$K$319,"Intermediate") -> 18 | F6: =COUNTIFS('Term Map'!$B$2:$B$319,A6,'Term Map'!$K$2:$K$319,"Advanced") -> 3 | G6: =COUNTIFS('Term Map'!$B$2:$B$319,A6,'Term Map'!$N$2:$N$319,"Verified")+COUNTIFS('Term Map'!$B$2:$B$319,A6,'Term Map'!$N$2:$N$319,"Published") -> 0 | H6: =IFERROR(G6/C6,0) -> 0
A7: 06 Purchasing and Contracts | B7: Requisitions, RFQs, purchase orders, receiving, invoicing, vendors and the different kinds of contracts. | C7: =COUNTIF('Term Map'!$B$2:$B$319,A7) -> 23 | D7: =COUNTIFS('Term Map'!$B$2:$B$319,A7,'Term Map'!$K$2:$K$319,"Beginner") -> 7 | E7: =COUNTIFS('Term Map'!$B$2:$B$319,A7,'Term Map'!$K$2:$K$319,"Intermediate") -> 11 | F7: =COUNTIFS('Term Map'!$B$2:$B$319,A7,'Term Map'!$K$2:$K$319,"Advanced") -> 5 | G7: =COUNTIFS('Term Map'!$B$2:$B$319,A7,'Term Map'!$N$2:$N$319,"Verified")+COUNTIFS('Term Map'!$B$2:$B$319,A7,'Term Map'!$N$2:$N$319,"Published") -> 0 | H7: =IFERROR(G7/C7,0) -> 0
A8: 07 Labor, Crafts and Scheduling | B8: People, users and labor, crafts, qualifications, calendars, crews and how planning differs from scheduling. | C8: =COUNTIF('Term Map'!$B$2:$B$319,A8) -> 17 | D8: =COUNTIFS('Term Map'!$B$2:$B$319,A8,'Term Map'!$K$2:$K$319,"Beginner") -> 5 | E8: =COUNTIFS('Term Map'!$B$2:$B$319,A8,'Term Map'!$K$2:$K$319,"Intermediate") -> 9 | F8: =COUNTIFS('Term Map'!$B$2:$B$319,A8,'Term Map'!$K$2:$K$319,"Advanced") -> 3 | G8: =COUNTIFS('Term Map'!$B$2:$B$319,A8,'Term Map'!$N$2:$N$319,"Verified")+COUNTIFS('Term Map'!$B$2:$B$319,A8,'Term Map'!$N$2:$N$319,"Published") -> 0 | H8: =IFERROR(G8/C8,0) -> 0
A9: 08 Finance and Cost | B9: GL accounts, financial periods, currencies, planned vs actual cost and life-to-date cost. | C9: =COUNTIF('Term Map'!$B$2:$B$319,A9) -> 12 | D9: =COUNTIFS('Term Map'!$B$2:$B$319,A9,'Term Map'!$K$2:$K$319,"Beginner") -> 1 | E9: =COUNTIFS('Term Map'!$B$2:$B$319,A9,'Term Map'!$K$2:$K$319,"Intermediate") -> 8 | F9: =COUNTIFS('Term Map'!$B$2:$B$319,A9,'Term Map'!$K$2:$K$319,"Advanced") -> 3 | G9: =COUNTIFS('Term Map'!$B$2:$B$319,A9,'Term Map'!$N$2:$N$319,"Verified")+COUNTIFS('Term Map'!$B$2:$B$319,A9,'Term Map'!$N$2:$N$319,"Published") -> 0 | H9: =IFERROR(G9/C9,0) -> 0
A10: 09 Platform, Configuration and Administration | B10: Security, domains, Database Configuration, Application Designer, workflow, escalations, automation scripts and admin tools. | C10: =COUNTIF('Term Map'!$B$2:$B$319,A10) -> 23 | D10: =COUNTIFS('Term Map'!$B$2:$B$319,A10,'Term Map'!$K$2:$K$319,"Beginner") -> 2 | E10: =COUNTIFS('Term Map'!$B$2:$B$319,A10,'Term Map'!$K$2:$K$319,"Intermediate") -> 6 | F10: =COUNTIFS('Term Map'!$B$2:$B$319,A10,'Term Map'!$K$2:$K$319,"Advanced") -> 15 | G10: =COUNTIFS('Term Map'!$B$2:$B$319,A10,'Term Map'!$N$2:$N$319,"Verified")+COUNTIFS('Term Map'!$B$2:$B$319,A10,'Term Map'!$N$2:$N$319,"Published") -> 0 | H10: =IFERROR(G10/C10,0) -> 0
A11: 10 Integration, Data and Reporting | B11: The integration framework, REST API, data loading and quality, BIRT reports, KPIs and analytics. | C11: =COUNTIF('Term Map'!$B$2:$B$319,A11) -> 18 | D11: =COUNTIFS('Term Map'!$B$2:$B$319,A11,'Term Map'!$K$2:$K$319,"Beginner") -> 3 | E11: =COUNTIFS('Term Map'!$B$2:$B$319,A11,'Term Map'!$K$2:$K$319,"Intermediate") -> 4 | F11: =COUNTIFS('Term Map'!$B$2:$B$319,A11,'Term Map'!$K$2:$K$319,"Advanced") -> 11 | G11: =COUNTIFS('Term Map'!$B$2:$B$319,A11,'Term Map'!$N$2:$N$319,"Verified")+COUNTIFS('Term Map'!$B$2:$B$319,A11,'Term Map'!$N$2:$N$319,"Published") -> 0 | H11: =IFERROR(G11/C11,0) -> 0
A12: 11 MAS Platform, Deployment and Licensing | B12: What MAS is, how it differs from 7.6, OpenShift architecture, workspaces, deployment options and AppPoints licensing. | C12: =COUNTIF('Term Map'!$B$2:$B$319,A12) -> 24 | D12: =COUNTIFS('Term Map'!$B$2:$B$319,A12,'Term Map'!$K$2:$K$319,"Beginner") -> 4 | E12: =COUNTIFS('Term Map'!$B$2:$B$319,A12,'Term Map'!$K$2:$K$319,"Intermediate") -> 12 | F12: =COUNTIFS('Term Map'!$B$2:$B$319,A12,'Term Map'!$K$2:$K$319,"Advanced") -> 8 | G12: =COUNTIFS('Term Map'!$B$2:$B$319,A12,'Term Map'!$N$2:$N$319,"Verified")+COUNTIFS('Term Map'!$B$2:$B$319,A12,'Term Map'!$N$2:$N$319,"Published") -> 0 | H12: =IFERROR(G12/C12,0) -> 0
A13: 12 MAS Applications: Monitor, Health, Predict, Mobile, AI | B13: Monitor, Health, Predict, Visual Inspection, Maximo Mobile, Optimizer and the AI features in MAS. | C13: =COUNTIF('Term Map'!$B$2:$B$319,A13) -> 28 | D13: =COUNTIFS('Term Map'!$B$2:$B$319,A13,'Term Map'!$K$2:$K$319,"Beginner") -> 6 | E13: =COUNTIFS('Term Map'!$B$2:$B$319,A13,'Term Map'!$K$2:$K$319,"Intermediate") -> 12 | F13: =COUNTIFS('Term Map'!$B$2:$B$319,A13,'Term Map'!$K$2:$K$319,"Advanced") -> 10 | G13: =COUNTIFS('Term Map'!$B$2:$B$319,A13,'Term Map'!$N$2:$N$319,"Verified")+COUNTIFS('Term Map'!$B$2:$B$319,A13,'Term Map'!$N$2:$N$319,"Published") -> 0 | H13: =IFERROR(G13/C13,0) -> 0
... A15: 14 Maintenance and Reliability Concepts | B15: The maintenance and reliability ideas behind Maximo: strategies, RCM, FMEA, P-F curve, MTBF, MTTR and other metrics. | C15: =COUNTIF('Term Map'!$B$2:$B$319,A15) -> 23 | D15: =COUNTIFS('Term Map'!$B$2:$B$319,A15,'Term Map'!$K$2:$K$319,"Beginner") -> 8 | E15: =COUNTIFS('Term Map'!$B$2:$B$319,A15,'Term Map'!$K$2:$K$319,"Intermediate") -> 12 | F15: =COUNTIFS('Term Map'!$B$2:$B$319,A15,'Term Map'!$K$2:$K$319,"Advanced") -> 3 | G15: =COUNTIFS('Term Map'!$B$2:$B$319,A15,'Term Map'!$N$2:$N$319,"Verified")+COUNTIFS('Term Map'!$B$2:$B$319,A15,'Term Map'!$N$2:$N$319,"Published") -> 0 | H15: =IFERROR(G15/C15,0) -> 0
A16: Total | C16: =SUM(C2:C15) -> 318 | D16: =SUM(D2:D15) -> 94 | E16: =SUM(E2:E15) -> 140 | F16: =SUM(F2:F15) -> 84 | G16: =SUM(G2:G15) -> 0 | H16: =IFERROR(G16/C16,0) -> 0

Sheet Riverbend Water
A1: Riverbend Water Authority (fictional): the one organization used in every example
A2: A mid-sized municipal water utility. Keep these names consistent across the whole site so readers follow one asset through every concept.
A4: Record Type | B4: ID / Name | C4: Description | D4: Parent / Belongs To | E4: Used In (Modules)
A5: Organization | B5: RWA | C5: Riverbend Water Authority. Base currency CAD. | E5: 01, 08
A6: Site | B6: TP1 | C6: Riverbend Treatment Plant | D6: RWA | E6: All
A7: Site | B7: DIST | C7: Distribution Network (mains, valves, pump stations, hydrants) | D7: RWA | E7: 02, 13
A8: Site | B8: FLEET | C8: Fleet Yard (40 service trucks and equipment) | D8: RWA | E8: 13
A9: Item Set | B9: RWAITEMS | C9: Shared item catalog for all RWA sites | D9: RWA | E9: 01, 05
A10: Location System | B10: PROCESS | C10: Primary system at TP1, follows the water treatment process | D10: TP1 | E10: 02
A11: Location System | B11: ELECTRICAL | C11: Secondary system at TP1, follows the power feeds | D11: TP1 | E11: 02
A12: Location | B12: TP1-INTAKE | C12: Raw water intake area | D12: TP1 (PROCESS) | E12: 02
A13: Location | B13: TP1-INTAKE-PS | C13: Raw water intake pump position (where P-101 sits) | D13: TP1-INTAKE | E13: 02, 03
A14: Location | B14: TP1-FILT | C14: Filtration building | D14: TP1 (PROCESS) | E14: 02, 04
A15: Location | B15: TP1-CHEM | C15: Chemical feed room (chlorine hazard) | D15: TP1 (PROCESS) | E15: 04
A16: Location | B16: CENTRAL | C16: Main storeroom at TP1 (type STOREROOM) | D16: TP1 | E16: 05, 06
A17: Location | B17: DIST-STORE | C17: Distribution yard storeroom (type STOREROOM) | D17: DIST | E17: 05
... A31: Item | B31: 2040 | C31: Pump bearing | D31: RWAITEMS / CENTRAL | E31: 05
A32: Job Plan | B32: JP-SEAL-CENT | C32: Replace mechanical seal on centrifugal pump | E32: 04
A33: Job Plan | B33: JP-INSP-PUMP | C33: Quarterly pump inspection | E33: 04
A34: Job Plan | B34: JP-LOTO-PUMP | C34: Lockout steps, nested in other pump job plans | E34: 04
A35: PM | B35: PM-P101-QTR | C35: Quarterly inspection of P-101, 14-day lead time | D35: P-101 | E35: 04
A36: PM | B36: PM-P101-LUBE | C36: Lubrication every 500 run hours | D36: P-101 | E36: 04
A37: Route | B37: RT-TP1-DAILY | C37: Daily operator round: intake, filters, chemical feed, clearwell | D37: TP1 | E37: 04
A38: Safety Plan | B38: SP-PUMP-LOTO | C38: Rotating equipment, stored energy and confined space hazards | E38: 04
A39: Work Order | B39: 50231 | C39: Replace seal on P-101 (CM, priority 1). The main example work order. | D39: P-101 | E39: 03, 05, 08
A40: Work Order | B40: 50400 | C40: TP1 annual shutdown (parent with 37 children) | D40: TP1 | E40: 03, 07
A41: Service Request | B41: 3412 | C41: Water pooling under P-101, reported by an operator | D41: P-101 | E41: 03
A42: Purchase Order | B42: 22014 | C42: 4 x 1001-SEAL from Northshore Pump Supply | D42: CENTRAL | E42: 06
A43: Company | B43: Northshore Pump Supply | C43: Main parts vendor | D43: Company set | E43: 06
A44: Company | B44: Apex Pumps | C44: Manufacturer of P-101 and M-117 | D44: Company set | E44: 06
A45: Craft | B45: MECH / ELEC / INST / OPER | C45: Mechanic, electrician, instrument tech, operator | E45: 07
A46: Person / Labor | B46: Dev Patel (DPATEL) | C46: Journeyman mechanic, does most example jobs | D46: MECH | E46: 03, 07
A47: Person | B47: Ana Moreau | C47: Maintenance planner at TP1 | E47: 01, 03, 07
A48: Person Group | B48: TP1-SUPV | C48: Shift supervisors at TP1 | E48: 07, 09

Sheet Learning Paths
A1: Learning Path | B1: Step | C1: Term | D1: Term ID (linked) | E1: Difficulty (linked) | F1: Module (linked)
A2: 1. Your first week in Maximo | B2: 1 | C2: Organization | D2: =IFERROR(INDEX('Term Map'!$A$2:$A$319,MATCH(C2,'Term Map'!$D$2:$D$319,0)),"Not found") -> M01-001 | E2: =IFERROR(INDEX('Term Map'!$K$2:$K$319,MATCH(C2,'Term Map'!$D$2:$D$319,0)),"") -> Beginner | F2: =IFERROR(INDEX('Term Map'!$B$2:$B$319,MATCH(C2,'Term Map'!$D$2:$D$319,0)),"") -> 01 Foundations and Structure
A3: 1. Your first week in Maximo | B3: 2 | C3: Site | D3: =IFERROR(INDEX('Term Map'!$A$2:$A$319,MATCH(C3,'Term Map'!$D$2:$D$319,0)),"Not found") -> M01-002 | E3: =IFERROR(INDEX('Term Map'!$K$2:$K$319,MATCH(C3,'Term Map'!$D$2:$D$319,0)),"") -> Beginner | F3: =IFERROR(INDEX('Term Map'!$B$2:$B$319,MATCH(C3,'Term Map'!$D$2:$D$319,0)),"") -> 01 Foundations and Structure
A4: 1. Your first week in Maximo | B4: 3 | C4: Location | D4: =IFERROR(INDEX('Term Map'!$A$2:$A$319,MATCH(C4,'Term Map'!$D$2:$D$319,0)),"Not found") -> M02-001 | E4: =IFERROR(INDEX('Term Map'!$K$2:$K$319,MATCH(C4,'Term Map'!$D$2:$D$319,0)),"") -> Beginner | F4: =IFERROR(INDEX('Term Map'!$B$2:$B$319,MATCH(C4,'Term Map'!$D$2:$D$319,0)),"") -> 02 Assets and Locations
A5: 1. Your first week in Maximo | B5: 4 | C5: Asset | D5: =IFERROR(INDEX('Term Map'!$A$2:$A$319,MATCH(C5,'Term Map'!$D$2:$D$319,0)),"Not found") -> M02-008 | E5: =IFERROR(INDEX('Term Map'!$K$2:$K$319,MATCH(C5,'Term Map'!$D$2:$D$319,0)),"") -> Beginner | F5: =IFERROR(INDEX('Term Map'!$B$2:$B$319,MATCH(C5,'Term Map'!$D$2:$D$319,0)),"") -> 02 Assets and Locations
A6: 1. Your first week in Maximo | B6: 5 | C6: Asset Hierarchy | D6: =IFERROR(INDEX('Term Map'!$A$2:$A$319,MATCH(C6,'Term Map'!$D$2:$D$319,0)),"Not found") -> M02-009 | E6: =IFERROR(INDEX('Term Map'!$K$2:$K$319,MATCH(C6,'Term Map'!$D$2:$D$319,0)),"") -> Beginner | F6: =IFERROR(INDEX('Term Map'!$B$2:$B$319,MATCH(C6,'Term Map'!$D$2:$D$319,0)),"") -> 02 Assets and Locations
A7: 1. Your first week in Maximo | B7: 6 | C7: Service Request | D7: =IFERROR(INDEX('Term Map'!$A$2:$A$319,MATCH(C7,'Term Map'!$D$2:$D$319,0)),"Not found") -> M03-001 | E7: =IFERROR(INDEX('Term Map'!$K$2:$K$319,MATCH(C7,'Term Map'!$D$2:$D$319,0)),"") -> Beginner | F7: =IFERROR(INDEX('Term Map'!$B$2:$B$319,MATCH(C7,'Term Map'!$D$2:$D$319,0)),"") -> 03 Work Management
A8: 1. Your first week in Maximo | B8: 7 | C8: Work Order | D8: =IFERROR(INDEX('Term Map'!$A$2:$A$319,MATCH(C8,'Term Map'!$D$2:$D$319,0)),"Not found") -> M03-004 | E8: =IFERROR(INDEX('Term Map'!$K$2:$K$319,MATCH(C8,'Term Map'!$D$2:$D$319,0)),"") -> Beginner | F8: =IFERROR(INDEX('Term Map'!$B$2:$B$319,MATCH(C8,'Term Map'!$D$2:$D$319,0)),"") -> 03 Work Management
A9: 1. Your first week in Maximo | B9: 8 | C9: Work Order Lifecycle / Status Flow | D9: =IFERROR(INDEX('Term Map'!$A$2:$A$319,MATCH(C9,'Term Map'!$D$2:$D$319,0)),"Not found") -> M03-005 | E9: =IFERROR(INDEX('Term Map'!$K$2:$K$319,MATCH(C9,'Term Map'!$D$2:$D$319,0)),"") -> Beginner | F9: =IFERROR(INDEX('Term Map'!$B$2:$B$319,MATCH(C9,'Term Map'!$D$2:$D$319,0)),"") -> 03 Work Management
A10: 1. Your first week in Maximo | B10: 9 | C10: Work Type | D10: =IFERROR(INDEX('Term Map'!$A$2:$A$319,MATCH(C10,'Term Map'!$D$2:$D$319,0)),"Not found") -> M03-006 | E10: =IFERROR(INDEX('Term Map'!$K$2:$K$319,MATCH(C10,'Term Map'!$D$2:$D$319,0)),"") -> Beginner | F10: =IFERROR(INDEX('Term Map'!$B$2:$B$319,MATCH(C10,'Term Map'!$D$2:$D$319,0)),"") -> 03 Work Management
A11: 1. Your first week in Maximo | B11: 10 | C11: Plans Tab (Planned Work) | D11: =IFERROR(INDEX('Term Map'!$A$2:$A$319,MATCH(C11,'Term Map'!$D$2:$D$319,0)),"Not found") -> M03-009 | E11: =IFERROR(INDEX('Term Map'!$K$2:$K$319,MATCH(C11,'Term Map'!$D$2:$D$319,0)),"") -> Beginner | F11: =IFERROR(INDEX('Term Map'!$B$2:$B$319,MATCH(C11,'Term Map'!$D$2:$D$319,0)),"") -> 03 Work Management
A12: 1. Your first week in Maximo | B12: 11 | C12: Actuals Tab | D12: =IFERROR(INDEX('Term Map'!$A$2:$A$319,MATCH(C12,'Term Map'!$D$2:$D$319,0)),"Not found") -> M03-010 | E12: =IFERROR(INDEX('Term Map'!$K$2:$K$319,MATCH(C12,'Term Map'!$D$2:$D$319,0)),"") -> Beginner | F12: =IFERROR(INDEX('Term Map'!$B$2:$B$319,MATCH(C12,'Term Map'!$D$2:$D$319,0)),"") -> 03 Work Management
A13: 1. Your first week in Maximo | B13: 12 | C13: Job Plan | D13: =IFERROR(INDEX('Term Map'!$A$2:$A$319,MATCH(C13,'Term Map'!$D$2:$D$319,0)),"Not found") -> M04-001 | E13: =IFERROR(INDEX('Term Map'!$K$2:$K$319,MATCH(C13,'Term Map'!$D$2:$D$319,0)),"") -> Beginner | F13: =IFERROR(INDEX('Term Map'!$B$2:$B$319,MATCH(C13,'Term Map'!$D$2:$D$319,0)),"") -> 04 Planning: Job Plans, PMs, Routes and Safety
... A95: 6. Admin and configuration | B95: 16 | C95: Migration Manager | D95: =IFERROR(INDEX('Term Map'!$A$2:$A$319,MATCH(C95,'Term Map'!$D$2:$D$319,0)),"Not found") -> M09-022 | E95: =IFERROR(INDEX('Term Map'!$K$2:$K$319,MATCH(C95,'Term Map'!$D$2:$D$319,0)),"") -> Advanced | F95: =IFERROR(INDEX('Term Map'!$B$2:$B$319,MATCH(C95,'Term Map'!$D$2:$D$319,0)),"") -> 09 Platform, Configuration and Administration

Sheet Sources
A1: Source | B1: What it confirms | C1: URL
A2: IBM Support: Readme for Maximo Application Suite 9.2.0 | B2: MAS 9.2.0 release date (June 25, 2026) and the components included (Core, Manage, Optimizer, IoT, Monitor, Predict, AI Service). | C2: https://www.ibm.com/support/pages/node/7277376
A3: IBM: Licensing in Maximo Application Suite 9.1 (PDF) | B3: Applications covered by MAS licensing, including Manage, Monitor, Health, Predict and Real Estate and Facilities; AppPoints consumption tables. | C3: https://www.ibm.com/docs/en/SSRHPA_cd/pdf/mas_licensing_91.pdf
A4: IBM Support: End of Support Announcement for Maximo 7.6.1 | B4: Base support for Maximo Asset Management 7.6.1.x and related industry solutions ended September 30, 2025. | C4: https://www.ibm.com/support/pages/node/6570953
A5: IBM Support: Maximo 7.6.1.3 last interim fix | B5: Last interim fix for 7.6.1.x on September 30, 2025; support extension needed after that date. | C5: https://www.ibm.com/support/pages/node/7243602
A6: IBM Community: Important update for Maximo users | B6: Extended support for 7.6.x through September 30, 2026; architecture differences between 7.6 and MAS. | C6: https://community.ibm.com/community/user/asset-facilities/discussion/important-update-for-ibm-maximo-users
A7: IBM product update deck (user group, July 2025) | B7: MAS 9.1 GA June 24, 2025; Maximo Assistant, Asset Investment Planning, Real Estate and Facilities, Maintenance Cost Insights; direct upgrade from 7.6.0.10, 7.6.1.2, 7.6.1.3; Mobile Incident Reporter. | C7: https://pacmug.org/wp-content/uploads/2025/07/PacMUGS2505_MaximoApplicationSuiteUpdate_IBM.pdf
A8: IBM Support: MAS AI Service 9.2.x releases | B8: AI Service updates through 2026, including natural language query support for more Manage objects. | C8: https://www.ibm.com/support/pages/node/7270126
A9: Red Hat blog: MAS and OpenShift | B9: MAS application lineup and that MAS runs on Red Hat OpenShift. | C9: https://www.redhat.com/en/blog/ibm-maximo-application-suite-mas-and-red-hat-openshift
A10: IBM Docs (primary reference for every row) | B10: Search 'Maximo Application Suite' at ibm.com/docs and pick your exact version. Use the 'Verify In' column to find the right section. | C10: https://www.ibm.com/docs
